stereotacticframe/__init__.py
stereotacticframe/blob_detection.py
stereotacticframe/cli.py
stereotacticframe/frame_detector.py
stereotacticframe/frame_protocol.py
stereotacticframe/frames.py
stereotacticframe/preprocessor.py
stereotacticframe/slice_provider.py
stereotacticframe/transforms.py
stereotacticframe-0.7.1.dist-info/METADATA
stereotacticframe-0.7.1.dist-info/WHEEL
stereotacticframe-0.7.1.dist-info/entry_points.txt
stereotacticframe-0.7.1.dist-info/licenses/LICENSE
stereotacticframe-0.7.1.dist-info/RECORD
