Metadata-Version: 2.4
Name: StereotacticFrame
Version: 0.7.1
Summary: A python package to put medical images in frame alignment.
Project-URL: Repository, https://github.com/dwml/StereotacticFrame.git
Project-URL: Issues, https://github.com/dwml/StereotacticFrame/issues
Author-email: "Dirk W.M. Loeffen" <dwm.loeffen@hotmail.com>
License: MIT License
License-File: LICENSE
Classifier: Development Status :: 4 - Beta
Classifier: License :: OSI Approved :: MIT License
Classifier: Programming Language :: Python :: 3.9
Classifier: Programming Language :: Python :: 3.10
Classifier: Programming Language :: Python :: 3.11
Classifier: Programming Language :: Python :: 3.12
Classifier: Programming Language :: Python :: 3.13
Requires-Python: >=3.9
Requires-Dist: numpy>=1.26.0
Requires-Dist: pyvista>=0.44.0
Requires-Dist: simpleitk>=2.3.1
Requires-Dist: typer>=0.12.5
